permanentbis.cp311-win32.pyd
permanentbis-0.1.1.dist-info/LICENSE
permanentbis-0.1.1.dist-info/METADATA
permanentbis-0.1.1.dist-info/WHEEL
permanentbis-0.1.1.dist-info/top_level.txt
permanentbis-0.1.1.dist-info/RECORD
