Metadata-Version: 2.1
Name: permanentbis
Version: 0.1.1
Summary: Computing the permanent of a matrix.
Author-email: Pete Shadbolt <hello@peteshadbolt.co.uk>, Andrzej Kaczmarczyk <droodev@gmail.com>
Maintainer-email: Andrzej Kaczmarczyk <droodev@gmail.com>
License: The MIT License (MIT)
Project-URL: Repository, https://github.com/droodev/permanentbis
Classifier: Programming Language :: Python :: 3
Classifier: License :: OSI Approved :: MIT License
Classifier: Operating System :: OS Independent
Requires-Python: >=3.10
License-File: LICENSE
Requires-Dist: numpy>=2.1
